{
    "format_version": "1.20.10",
    "minecraft:item": {
        "description": {
            "identifier": "bsm:scrubber_tool",
            "menu_category": {
                "category": "equipment"
            }
        },
        "components": {
            "minecraft:icon": {
                "texture": "bsm_scrubber_tool"
            },
            "minecraft:display_name": {
                "value": "§eBSM: Timeline Scrubber"
            },
            "minecraft:stack_size": 1,
            "minecraft:hand_equipped": true
        }
    }
}